medusa/__init__.py
medusa/artifact_removal.py
medusa/classification_utils.py
medusa/compatibility.py
medusa/components.py
medusa/deep_learning_models.py
medusa/ecg.py
medusa/emg.py
medusa/eog.py
medusa/epoching.py
medusa/frequency_filtering.py
medusa/nirs.py
medusa/notify_me.py
medusa/optimization.py
medusa/performance_analysis.py
medusa/pytorch_integration.py
medusa/settings_schema.py
medusa/signal_generators.py
medusa/signal_orthogonalization.py
medusa/spatial_filtering.py
medusa/stats.py
medusa/transforms.py
medusa/utils.py
medusa/analysis/__init__.py
medusa/analysis/time_plot/__init__.py
medusa/analysis/time_plot/time_plot.py
medusa/analysis/time_plot/time_plot.ui
medusa/analysis/time_plot/icons/decrease_channels.png
medusa/analysis/time_plot/icons/download.png
medusa/analysis/time_plot/icons/ff.png
medusa/analysis/time_plot/icons/gear.png
medusa/analysis/time_plot/icons/increase_channels.png
medusa/analysis/time_plot/icons/medusa_task_icon.png
medusa/analysis/time_plot/icons/next_chapter.png
medusa/analysis/time_plot/icons/oldzoom_in.png
medusa/analysis/time_plot/icons/oldzoom_out.png
medusa/analysis/time_plot/icons/prev_chapter.png
medusa/analysis/time_plot/icons/rr.png
medusa/analysis/time_plot/icons/tab.png
medusa/analysis/time_plot/icons/zoom_in.png
medusa/analysis/time_plot/icons/zoom_out.png
medusa/bci/__init__.py
medusa/bci/cvep_spellers.py
medusa/bci/erp_spellers.py
medusa/bci/metrics.py
medusa/bci/mi_paradigms.py
medusa/bci/nft_paradigms.py
medusa/bci/ssvep_spellers.py
medusa/connectivity/__init__.py
medusa/connectivity/amplitude_connectivity.py
medusa/connectivity/frequency_connectivity.py
medusa/connectivity/phase_connectivity.py
medusa/graph_theory/__init__.py
medusa/graph_theory/assortativity.py
medusa/graph_theory/betweeenness_centrality.py
medusa/graph_theory/clustering_coefficient.py
medusa/graph_theory/complexity.py
medusa/graph_theory/degree.py
medusa/graph_theory/density.py
medusa/graph_theory/efficiency.py
medusa_kernel-1.4.3.dist-info/licenses/LICENSE
medusa_kernel-1.4.3.dist-info/METADATA
medusa_kernel-1.4.3.dist-info/WHEEL
medusa_kernel-1.4.3.dist-info/top_level.txt
medusa_kernel-1.4.3.dist-info/RECORD
