Metadata-Version: 2.4
Name: medusa-kernel
Version: 1.4.3
Summary: Advanced biosignal processing toolbox
Home-page: https://medusabci.com/
Author: Eduardo Santamaría-Vázquez, Víctor Martínez-Cagigal, Diego Marcos-Martínez, Víctor Rodríguez-González, Sergio Pérez-Velasco
Author-email: support@medusabci.com
License: CC Attribution-NonCommercial-NoDerivs 2.0
Keywords: Signal,Biosignal,EEG,BCI
Classifier: Development Status :: 4 - Beta
Classifier: Intended Audience :: Developers
Classifier: Topic :: Scientific/Engineering
Classifier: Programming Language :: Python
Requires-Python: >=3.10, <3.14
License-File: LICENSE
Requires-Dist: numpy
Requires-Dist: scipy
Requires-Dist: matplotlib
Requires-Dist: scikit-learn
Requires-Dist: statsmodels
Requires-Dist: bson
Requires-Dist: h5py
Requires-Dist: dill
Requires-Dist: tqdm
Requires-Dist: PySide6
Requires-Dist: PyWavelets
Dynamic: author
Dynamic: author-email
Dynamic: classifier
Dynamic: description
Dynamic: description-content-type
Dynamic: home-page
Dynamic: keywords
Dynamic: license
Dynamic: license-file
Dynamic: requires-dist
Dynamic: requires-python
Dynamic: summary
